popcast/__init__.py
popcast/cli.py
popcast/cross_immunity.py
popcast/fit.py
popcast/forecast.py
popcast/metrics.py
popcast/nextcast.py
popcast/utils.py
popcast/weighted_distances.py
popcast-2.0.0.dist-info/entry_points.txt
popcast-2.0.0.dist-info/licenses/LICENSE
popcast-2.0.0.dist-info/WHEEL
popcast-2.0.0.dist-info/METADATA
popcast-2.0.0.dist-info/RECORD
