Metadata-Version: 2.4
Name: popcast
Version: 2.0.0
Summary: Long-term forecasts for pathogen populations
Author-email: John Huddleston <huddlej@gmail.com>
Requires-Python: >=3.6
Classifier: Programming Language :: Python :: 3
Classifier: License :: OSI Approved :: MIT License
Classifier: Operating System :: OS Independent
License-File: LICENSE
Requires-Dist: jellyfish >=0.8.2, ==0.*
Requires-Dist: numpy >=1.17.0, ==1.*
Requires-Dist: pandas >=1.2.0, ==1.*
Requires-Dist: scipy >=1.5.4, ==1.*
Requires-Dist: opencv-python >=4.5, ==4.* ; extra == "full"
Requires-Dist: coverage[toml] >=5.2.1, ==5.* ; extra == "test"
Requires-Dist: cram >=0.7, ==0.* ; extra == "test"
Requires-Dist: flake8 >=3.9.0, ==3.* ; extra == "test"
Requires-Dist: pylint >=2.14.5, ==2.* ; extra == "test"
Project-URL: Bug Tracker, https://github.com/blab/popcast/issues
Project-URL: Homepage, https://github.com/blab/popcast
Provides-Extra: full
Provides-Extra: test
